<?xml version="1.0" encoding="utf-8" ?><dwsync><file name="style1.css" server="dasl.mem.drexel.edu/public_html/" local="3469998612" remote="318763443862894771" Dst="-1" /><file name="style2.css" server="dasl.mem.drexel.edu/public_html/" local="3464433969" remote="318763443857330282" Dst="-1" /><file name="index_style2.css" server="dasl.mem.drexel.edu/public_html/" local="3474187648" remote="318763443867083669" Dst="-1" /><file name="index_button_style2.css" server="dasl.mem.drexel.edu/public_html/" local="3474188153" remote="318763443867098427" Dst="-1" /><file name="sticky_footer.css" server="dasl.mem.drexel.edu/public_html/" local="3474380268" remote="318763443867276287" Dst="-1" /><file name="index_button_style3.css" server="dasl.mem.drexel.edu/public_html/" local="3478522565" remote="318763443871418455" Dst="-1" /><file name="index_style3.css" server="dasl.mem.drexel.edu/public_html/" local="3474546346" remote="318763443867442350" Dst="-1" /><file name="style3.css" server="dasl.mem.drexel.edu/public_html/" local="3479117916" remote="318763443872014414" Dst="-1" /><file name="VerticalSlidingAccordion_overrides.css" server="dasl.mem.drexel.edu/public_html/" local="3477486096" remote="318763443870382017" Dst="-1" /><file name="DirectionAwareHoverEffect_overrides.css" server="dasl.mem.drexel.edu/public_html/" local="3478524456" remote="318763443871420345" Dst="-1" /></dwsync>